pyforbes/__init__.py
pyforbes/exceptions.py
pyforbes/lists.py
pyforbes/tests/__init__.py
pyforbes/tests/conftest.py
pyforbes/tests/fixtures.py
pyforbes/tests/test_forbeslist.py
pyforbes/utils/__init__.py
pyforbes/utils/constants.py
pyforbes/utils/lists_config.py
pyforbes/utils/requests.py
pyforbes-1.0.3.dist-info/LICENSE
pyforbes-1.0.3.dist-info/METADATA
pyforbes-1.0.3.dist-info/WHEEL
pyforbes-1.0.3.dist-info/top_level.txt
pyforbes-1.0.3.dist-info/RECORD
