Metadata-Version: 2.1
Name: pyforbes
Version: 1.0.3
Summary: Python package to collect data from Forbes.
Home-page: https://github.com/laxmena/PyForbes
Author: laxmena
Author-email: ConnectWith@laxmena.com
License: MIT
Download-URL: https://github.com/laxmena/PyForbes
Project-URL: Bug Tracker, https://github.com/laxmena/PyForbes/issues
Project-URL: CI: Circle, https://circleci.com/gh/pyforbes/pyforbes
Project-URL: GitHub: repo, https://github.com/pyforbes/pyforbes
Keywords: python forbes api pyforbes
Platform: UNKNOWN
Classifier: Programming Language :: Python :: 3
Classifier: License :: OSI Approved :: MIT License
Classifier: Operating System :: OS Independent
Classifier: Topic :: Scientific/Engineering :: Information Analysis
Classifier: Topic :: Office/Business :: Financial
Classifier: Topic :: Office/Business
Classifier: Topic :: Office/Business :: Financial :: Investment
Classifier: License :: OSI Approved :: MIT License
Classifier: Topic :: Software Development
Classifier: Programming Language :: Python :: 3.6
Classifier: Programming Language :: Python :: 3.7
Classifier: Programming Language :: Python :: 3.8
Classifier: Programming Language :: Python :: 3.9
Classifier: Topic :: Utilities
Requires-Python: >=3.6
License-File: LICENSE
Requires-Dist: pandas (>=1.1.3)
Requires-Dist: numpy
Requires-Dist: requests
Provides-Extra: docs
Requires-Dist: sphinx ; extra == 'docs'
Requires-Dist: docutils ; extra == 'docs'
Requires-Dist: alabaster ; extra == 'docs'
Requires-Dist: setuptools ; extra == 'docs'
